AnimeBot/__init__.py
SexyNutella-9.0.0.dist-info/METADATA
SexyNutella-9.0.0.dist-info/WHEEL
SexyNutella-9.0.0.dist-info/top_level.txt
SexyNutella-9.0.0.dist-info/RECORD
