Metadata-Version: 2.1
Name: SexyNutella
Version: 9.0.0
Summary: A Multi Action Discord Bot Based On Anime
Home-page: https://github.com/PirxcyFinal/AnimeBot/
Author: Pirxcy
License: UNKNOWN
Platform: UNKNOWN
Classifier: Programming Language :: Python :: 3
Classifier: License :: OSI Approved :: MIT License
Classifier: Operating System :: OS Independent
Requires-Dist: crayons
Requires-Dist: dhooks
Requires-Dist: discord.py
Requires-Dist: timeago
Requires-Dist: jinja2
Requires-Dist: jaconv
Requires-Dist: requests
Requires-Dist: psutil
Requires-Dist: pypresence
Requires-Dist: uvloop
Requires-Dist: sanic
Requires-Dist: aiohttp
